README.md
setup.py
ec2_security_groups_dumper/__init__.py
ec2_security_groups_dumper/main.py
ec2_security_groups_dumper.egg-info/PKG-INFO
ec2_security_groups_dumper.egg-info/SOURCES.txt
ec2_security_groups_dumper.egg-info/dependency_links.txt
ec2_security_groups_dumper.egg-info/entry_points.txt
ec2_security_groups_dumper.egg-info/requires.txt
ec2_security_groups_dumper.egg-info/top_level.txt