Metadata-Version: 1.1
Name: ec2-security-groups-dumper
Version: 1.8.0
Summary: AWS EC2 Security Groups dump tool
Home-page: https://github.com/percolate/ec2-security-groups-dumper
Author: Laurent Raufaste
Author-email: analogue@glop.org
License: GPLv3
Keywords: aws ec2 firewall boto3
Platform: UNKNOWN
Classifier: Development Status :: 4 - Beta
Classifier: Environment :: Console
Classifier: Intended Audience :: System Administrators
Classifier: License :: OSI Approved :: GNU General Public License v3 (GPLv3)
Classifier: Natural Language :: English
Classifier: Operating System :: POSIX
Classifier: Programming Language :: Python
Classifier: Topic :: System :: Systems Administration
